tinybrain/accelerated.hpp
tinybrain/accelerated.pyx
tinybrain/accelerated.cpython-313-x86_64-linux-gnu.so
tinybrain/downsample.py
tinybrain/__init__.py
tinybrain-1.7.0.dist-info/AUTHORS
tinybrain-1.7.0.dist-info/LICENSE
tinybrain-1.7.0.dist-info/WHEEL
tinybrain-1.7.0.dist-info/RECORD
tinybrain-1.7.0.dist-info/pbr.json
tinybrain-1.7.0.dist-info/top_level.txt
tinybrain-1.7.0.dist-info/METADATA
